odoo/addons/sale_coupon_incompatibility/README.rst
odoo/addons/sale_coupon_incompatibility/__init__.py
odoo/addons/sale_coupon_incompatibility/__manifest__.py
odoo/addons/sale_coupon_incompatibility/i18n/es.po
odoo/addons/sale_coupon_incompatibility/i18n/sale_coupon_incompatibility.pot
odoo/addons/sale_coupon_incompatibility/models/__init__.py
odoo/addons/sale_coupon_incompatibility/models/coupon_program.py
odoo/addons/sale_coupon_incompatibility/models/sale_coupon.py
odoo/addons/sale_coupon_incompatibility/readme/CONTRIBUTORS.rst
odoo/addons/sale_coupon_incompatibility/readme/DESCRIPTION.rst
odoo/addons/sale_coupon_incompatibility/readme/USAGE.rst
odoo/addons/sale_coupon_incompatibility/static/description/icon.png
odoo/addons/sale_coupon_incompatibility/static/description/icon.svg
odoo/addons/sale_coupon_incompatibility/static/description/index.html
odoo/addons/sale_coupon_incompatibility/tests/__init__.py
odoo/addons/sale_coupon_incompatibility/tests/test_sale_coupon_incompatibility.py
odoo_addon_sale_coupon_incompatibility-15.0.1.0.0.6.dist-info/METADATA
odoo_addon_sale_coupon_incompatibility-15.0.1.0.0.6.dist-info/WHEEL
odoo_addon_sale_coupon_incompatibility-15.0.1.0.0.6.dist-info/top_level.txt
odoo_addon_sale_coupon_incompatibility-15.0.1.0.0.6.dist-info/RECORD
